sss_beneficiarios_hospitales/__init__.py
sss_beneficiarios_hospitales/data.py
sss_beneficiarios_hospitales/parser.py
sss_beneficiarios_hospitales/html-samples/full-afiliado-con-empleador.html
sss_beneficiarios_hospitales/html-samples/full-afiliado.html
sss_beneficiarios_hospitales/html-samples/full-sin-datos.html
sss_beneficiarios_hospitales-0.8.120.dist-info/LICENSE
sss_beneficiarios_hospitales-0.8.120.dist-info/METADATA
sss_beneficiarios_hospitales-0.8.120.dist-info/WHEEL
sss_beneficiarios_hospitales-0.8.120.dist-info/top_level.txt
sss_beneficiarios_hospitales-0.8.120.dist-info/RECORD
