Metadata-Version: 2.1
Name: sss-beneficiarios-hospitales
Version: 0.8.120
Summary: API Superintendencia de Servicios de Salud Argentino para informacion sobre beneficiarios de hospitales
Home-page: https://github.com/cluster311/sss-beneficiarios
Author: Andres Vazquez
Author-email: andres@data99.com.ar
License: MIT
Platform: UNKNOWN
Classifier: Programming Language :: Python :: 3
Classifier: Programming Language :: Python :: 3.6
Classifier: Programming Language :: Python :: 3.7
Classifier: Programming Language :: Python :: 3.8
Classifier: License :: OSI Approved :: MIT License
Classifier: Operating System :: OS Independent
Classifier: Intended Audience :: Developers
Requires-Python: >=3.6
Requires-Dist: requests (>=2.24)
Requires-Dist: beautifulsoup4 (>=4.9.1)
Requires-Dist: html5lib (>=1.1)
